latticestockdataclient/__init__.py
latticestockdataclient/data/__init__.py
latticestockdataclient/data/economy.py
latticestockdataclient/data/market.py
latticestockdataclient/data/stock/__init__.py
latticestockdataclient/data/stock/company_info.py
latticestockdataclient/data/stock/financials.py
latticestockdataclient/data/stock/historical_prices.py
latticestockdataclient/data/stock/news.py
latticestockdataclient/data/stock/stats.py
latticestockdataclient/data/stock/valuation.py
latticestockdataclient/util/LatticeStockDataAccessor.py
latticestockdataclient/util/LatticeStockDataPayloadFactory.py
latticestockdataclient/util/__init__.py
latticestockdataclient/util/ttlcache.py
LatticeStockDataClient-0.0.4.dist-info/LICENSE
LatticeStockDataClient-0.0.4.dist-info/METADATA
LatticeStockDataClient-0.0.4.dist-info/WHEEL
LatticeStockDataClient-0.0.4.dist-info/top_level.txt
LatticeStockDataClient-0.0.4.dist-info/RECORD
