Metadata-Version: 2.1
Name: LatticeStockDataClient
Version: 0.0.4
Summary: An API for gathering RapidAPI stock info
Home-page: UNKNOWN
Author: darrylbckhm@gmail.com
License: UNKNOWN
Platform: UNKNOWN
Classifier: Development Status :: 4 - Beta
Classifier: Intended Audience :: Developers
Classifier: License :: OSI Approved :: Apache Software License
Classifier: Programming Language :: Python :: 3 :: Only
Requires-Python: >=3.9
Requires-Dist: pytest
Requires-Dist: requests
Requires-Dist: cachetools
Requires-Dist: bson
